[
    {
        "username": "hmyron",
        "fullname": "Myron Harwood",
        "location": "Dayu",
        "avatar": "https://robohash.org/magnidolorin.jpg?size=50x50&set=set1"
    },
    {
        "username": "vmarcellina",
        "fullname": "Marcellina Vossgen",
        "location": "Jinglongqiao",
        "avatar": "https://robohash.org/sednonaut.bmp?size=50x50&set=set1"
    },
    {
        "username": "bwally",
        "fullname": "Wally Burburough",
        "location": "New Leyte",
        "avatar": "https://robohash.org/consequaturetaperiam.jpg?size=50x50&set=set1"
    },
    {
        "username": "dwake",
        "fullname": "Wake Dugood",
        "location": "Valky",
        "avatar": "https://robohash.org/atvoluptatibusodio.bmp?size=50x50&set=set1"
    },
    {
        "username": "tbobbie",
        "fullname": "Bobbie Tacker",
        "location": "Hotaka",
        "avatar": "https://robohash.org/quiaperferendisquae.jpg?size=50x50&set=set1"
    },
    {
        "username": "calys",
        "fullname": "Alys Carvell",
        "location": "Golomunta",
        "avatar": "https://robohash.org/autofficiislaudantium.bmp?size=50x50&set=set1"
    },
    {
        "username": "gantoine",
        "fullname": "Antoine Giacomazzo",
        "location": "Babakan",
        "avatar": "https://robohash.org/sapienteaipsam.png?size=50x50&set=set1"
    },
    {
        "username": "hleila",
        "fullname": "Leila De La Haye",
        "location": "Redange-sur-Attert",
        "avatar": "https://robohash.org/temporaasperioresquis.png?size=50x50&set=set1"
    },
    {
        "username": "lnanice",
        "fullname": "Nanice Lovewell",
        "location": "Dunhua",
        "avatar": "https://robohash.org/dolorsuntest.png?size=50x50&set=set1"
    },
    {
        "username": "temilio",
        "fullname": "Emilio Thormann",
        "location": "Bayasgalant",
        "avatar": "https://robohash.org/enimdebitissit.bmp?size=50x50&set=set1"
    }
]